[
  {
    "id": "edge-ncip-1.4.0",
    "action": "enable"
  },
  {
    "id": "edge-orders-2.3.0",
    "action": "enable"
  },
  {
    "id": "edge-oai-pmh-2.3.0",
    "action": "enable"
  },
  {
    "id": "edge-patron-4.3.0",
    "action": "enable"
  },
  {
    "id": "edge-rtac-2.1.1",
    "action": "enable"
  },
  {
    "id": "edge-sip2-1.4.0",
    "action": "enable"
  },
  {
    "id": "mod-aes-0.0.3",
    "action": "enable"
  },
  {
    "id": "mod-audit-1.0.2",
    "action": "enable"
  },
  {
    "id": "mod-codex-inventory-1.8.0",
    "action": "enable"
  },
  {
    "id": "mod-codex-ekb-1.7.2",
    "action": "enable"
  },
  {
    "id": "mod-data-import-converter-storage-1.9.2",
    "action": "enable"
  },
  {
    "id": "mod-erm-usage-harvester-2.0.2",
    "action": "enable"
  },
  {
    "id": "mod-gobi-1.11.0",
    "action": "enable"
  },
  {
    "id": "mod-ncip-1.6.1",
    "action": "enable"
  },
  {
    "id": "mod-patron-4.3.0",
    "action": "enable"
  },
  {
    "id": "mod-rtac-2.0.1",
    "action": "enable"
  },
  {
    "id": "mod-user-import-3.2.1",
    "action": "enable"
  },
  {
    "id": "okapi-4.2.2",
    "action": "enable"
  }
]
