[
  {
    "id": "folio_acquisition-units-2.2.100080",
    "action": "enable"
  },
  {
    "id": "folio_agreements-5.1.1000594",
    "action": "enable"
  },
  {
    "id": "folio_calendar-5.0.100090",
    "action": "enable"
  },
  {
    "id": "folio_checkin-4.0.1000321",
    "action": "enable"
  },
  {
    "id": "folio_checkout-5.0.1000485",
    "action": "enable"
  },
  {
    "id": "folio_circulation-5.0.1000594",
    "action": "enable"
  },
  {
    "id": "folio_circulation-log-1.0.100042",
    "action": "enable"
  },
  {
    "id": "folio_courses-3.1.2000311",
    "action": "enable"
  },
  {
    "id": "folio_data-export-3.0.2000205",
    "action": "enable"
  },
  {
    "id": "folio_data-import-3.0.3000715",
    "action": "enable"
  },
  {
    "id": "folio_developer-4.0.1000168",
    "action": "enable"
  },
  {
    "id": "folio_eholdings-5.0.1000836",
    "action": "enable"
  },
  {
    "id": "folio_erm-comparisons-1.1.100061",
    "action": "enable"
  },
  {
    "id": "folio_erm-usage-4.0.1000245",
    "action": "enable"
  },
  {
    "id": "folio_finance-2.2.1000404",
    "action": "enable"
  },
  {
    "id": "folio_inventory-5.0.10001103",
    "action": "enable"
  },
  {
    "id": "folio_invoice-2.2.2000375",
    "action": "enable"
  },
  {
    "id": "folio_ldp-1.1.100015",
    "action": "enable"
  },
  {
    "id": "folio_licenses-5.1.1000348",
    "action": "enable"
  },
  {
    "id": "folio_local-kb-admin-3.1.1000138",
    "action": "enable"
  },
  {
    "id": "folio_marccat-3.0.1000436",
    "action": "enable"
  },
  {
    "id": "folio_myprofile-4.0.1000108",
    "action": "enable"
  },
  {
    "id": "folio_notes-5.0.100071",
    "action": "enable"
  },
  {
    "id": "folio_oai-pmh-1.3.100086",
    "action": "enable"
  },
  {
    "id": "folio_orders-2.2.6000920",
    "action": "enable"
  },
  {
    "id": "folio_organizations-2.2.1000318",
    "action": "enable"
  },
  {
    "id": "folio_plugin-create-inventory-records-2.0.100045",
    "action": "enable"
  },
  {
    "id": "folio_plugin-find-agreement-5.0.100080",
    "action": "enable"
  },
  {
    "id": "folio_plugin-find-contact-2.2.100072",
    "action": "enable"
  },
  {
    "id": "folio_plugin-find-eresource-1.0.100024",
    "action": "enable"
  },
  {
    "id": "folio_plugin-find-erm-usage-data-provider-2.0.100042",
    "action": "enable"
  },
  {
    "id": "folio_plugin-find-import-profile-3.0.100064",
    "action": "enable"
  },
  {
    "id": "folio_plugin-find-instance-4.0.100058",
    "action": "enable"
  },
  {
    "id": "folio_plugin-find-interface-2.2.100063",
    "action": "enable"
  },
  {
    "id": "folio_plugin-find-license-5.1.100082",
    "action": "enable"
  },
  {
    "id": "folio_plugin-find-organization-2.2.100064",
    "action": "enable"
  },
  {
    "id": "folio_plugin-find-package-title-2.0.100027",
    "action": "enable"
  },
  {
    "id": "folio_plugin-find-po-line-2.2.100077",
    "action": "enable"
  },
  {
    "id": "folio_plugin-find-user-4.0.1000134",
    "action": "enable"
  },
  {
    "id": "folio_quick-marc-2.0.100097",
    "action": "enable"
  },
  {
    "id": "folio_receiving-1.2.1000192",
    "action": "enable"
  },
  {
    "id": "folio_remote-storage-1.0.10006",
    "action": "enable"
  },
  {
    "id": "folio_requests-4.0.1000596",
    "action": "enable"
  },
  {
    "id": "folio_search-3.1.1000201",
    "action": "enable"
  },
  {
    "id": "folio_servicepoints-4.0.100082",
    "action": "enable"
  },
  {
    "id": "folio_stripes-core-7.0.1000808",
    "action": "enable"
  },
  {
    "id": "folio_stripes-smart-components-6.0.1000886",
    "action": "enable"
  },
  {
    "id": "folio_tags-4.0.100066",
    "action": "enable"
  },
  {
    "id": "folio_tenant-settings-5.0.1000161",
    "action": "enable"
  },
  {
    "id": "folio_users-6.0.10001333",
    "action": "enable"
  },
  {
    "id": "edge-ncip-1.7.0-SNAPSHOT.17",
    "action": "enable"
  },
  {
    "id": "edge-orders-2.4.0-SNAPSHOT.41",
    "action": "enable"
  },
  {
    "id": "edge-oai-pmh-2.3.1-SNAPSHOT.60",
    "action": "enable"
  },
  {
    "id": "edge-patron-4.3.1-SNAPSHOT.56",
    "action": "enable"
  },
  {
    "id": "edge-rtac-2.2.0-SNAPSHOT.67",
    "action": "enable"
  },
  {
    "id": "edge-sip2-1.5.0-SNAPSHOT.50",
    "action": "enable"
  }
]
